odoo9_addon_pos_quick_logout-9.0.1.0.0-py2.7-nspkg.pth
odoo9_addon_pos_quick_logout-9.0.1.0.0.dist-info/top_level.txt
odoo9_addon_pos_quick_logout-9.0.1.0.0.dist-info/WHEEL
odoo9_addon_pos_quick_logout-9.0.1.0.0.dist-info/RECORD
odoo9_addon_pos_quick_logout-9.0.1.0.0.dist-info/metadata.json
odoo9_addon_pos_quick_logout-9.0.1.0.0.dist-info/DESCRIPTION.rst
odoo9_addon_pos_quick_logout-9.0.1.0.0.dist-info/METADATA
odoo9_addon_pos_quick_logout-9.0.1.0.0.dist-info/namespace_packages.txt
odoo_addons/pos_quick_logout/__openerp__.py
odoo_addons/pos_quick_logout/__init__.py
odoo_addons/pos_quick_logout/README.rst
odoo_addons/pos_quick_logout/i18n/fr.po
odoo_addons/pos_quick_logout/static/description/cashier_user_different.png
odoo_addons/pos_quick_logout/static/description/cashier_user_identical.png
odoo_addons/pos_quick_logout/static/description/icon.png
odoo_addons/pos_quick_logout/static/src/js/pos_quick_logout.js
odoo_addons/pos_quick_logout/static/src/css/pos_quick_logout.css
odoo_addons/pos_quick_logout/static/src/xml/templates.xml
odoo_addons/pos_quick_logout/static/src/xml/pos_quick_logout.xml
