Metadata-Version: 2.0
Name: odoo9-addon-pos-quick-logout
Version: 9.0.1.0.0
Summary: Allow PoS user to logout quickly after user changed
Home-page: http://www.lalouve.net
Author: UNKNOWN
Author-email: UNKNOWN
License: UNKNOWN
Platform: UNKNOWN
Requires-Dist: odoo (<9.1a,>=9.0a)
Classifier: Programming Language :: Python :: 2.7
Classifier: Framework :: Odoo
